Metadata-Version: 1.0
Name: cfgtool
Version: 0.3.post6
Summary: Cfgtool configuration management
Home-page: https://pypi.python.org/pypi/cfgtool
Author: J C Lawrence
Author-email: claw@kanga.nu
License: LGPL v3.0
Keywords: configuration management
Platform: UNKNOWN
